{
  "session_id": "acura_daytona_international_speedway_acuraarx06gtp_daytona_2011_road_2026-04-03_20-31-55",
  "ibt_path": "ibtfiles\\acuraarx06gtp_daytona 2011 road 2026-04-03 20-31-55.ibt",
  "car": "acura",
  "track": "Daytona International Speedway",
  "track_config": "Road Course",
  "timestamp": "2026-04-04T02:55:19.862692+00:00",
  "ibt_date": "",
  "setup": {
    "wing": 8.0,
    "adapter_name": "acura",
    "fuel_l": 58.0,
    "fuel_low_warning_l": 10.0,
    "fuel_target_l": 0.0,
    "front_rh_static": 30.0,
    "rear_rh_static": 44.9,
    "front_pushrod": -30.5,
    "rear_pushrod": -33.0,
    "front_heave_nmm": 360.0,
    "rear_third_nmm": 170.0,
    "torsion_bar_od_mm": 14.34,
    "rear_spring_nmm": 0.0,
    "front_heave_index": 360.0,
    "rear_heave_index": 170.0,
    "front_torsion_bar_index": 14.34,
    "rear_torsion_bar_index": 0.0,
    "front_arb_size": "Soft",
    "front_arb_blade": 1,
    "rear_arb_size": "Soft",
    "rear_arb_blade": 3,
    "front_camber_deg": -2.8,
    "rear_camber_deg": -1.8,
    "front_toe_mm": -0.2,
    "rear_toe_mm": -0.0,
    "brake_bias_pct": 47.0,
    "brake_bias_target": 0.0,
    "brake_bias_migration": 0.0,
    "brake_bias_migration_gain": 0.0,
    "front_master_cyl_mm": 20.6,
    "rear_master_cyl_mm": 22.2,
    "pad_compound": "Medium",
    "front_diff_preload_nm": 0.0,
    "diff_preload_nm": 20.0,
    "diff_ramp_label": "40/65",
    "diff_clutch_plates": 4,
    "tc_gain": 5,
    "tc_slip": 5,
    "gear_stack": "Long",
    "speed_in_first_kph": 155.4,
    "speed_in_second_kph": 189.4,
    "speed_in_third_kph": 218.6,
    "speed_in_fourth_kph": 250.0,
    "speed_in_fifth_kph": 286.9,
    "speed_in_sixth_kph": 321.4,
    "speed_in_seventh_kph": 355.2,
    "hybrid_rear_drive_enabled": "",
    "hybrid_rear_drive_corner_pct": 0.0,
    "roof_light_color": "Purple",
    "dampers": {
      "lf": {
        "ls_comp": 3,
        "ls_rbd": 2,
        "hs_comp": 5,
        "hs_rbd": 4,
        "hs_slope": 10
      },
      "rf": {
        "ls_comp": 3,
        "ls_rbd": 2,
        "hs_comp": 5,
        "hs_rbd": 4,
        "hs_slope": 10
      },
      "lr": {
        "ls_comp": 8,
        "ls_rbd": 5,
        "hs_comp": 9,
        "hs_rbd": 7,
        "hs_slope": 10
      },
      "rr": {
        "ls_comp": 8,
        "ls_rbd": 5,
        "hs_comp": 9,
        "hs_rbd": 7,
        "hs_slope": 10
      }
    },
    "roll_dampers": {
      "front": {
        "ls": 2,
        "hs": 4
      },
      "rear": {
        "ls": 9,
        "hs": 8
      }
    },
    "rear_torsion_od_mm": 15.14
  },
  "performance": {
    "best_lap_time_s": 94.9359359741211,
    "lap_number": 3,
    "median_speed_kph": 217.8,
    "max_speed_kph": 318.6,
    "consistency_cv": 0.0029883550819082127
  },
  "telemetry": {
    "dynamic_front_rh_mm": 17.174320220947266,
    "dynamic_rear_rh_mm": 28.53964614868164,
    "front_rh_std_mm": 7.590301513671875,
    "rear_rh_std_mm": 8.701332092285156,
    "front_shock_vel_p95_mps": 0.13317713141441345,
    "rear_shock_vel_p95_mps": 0.2133111208677292,
    "front_shock_vel_p99_mps": 0.29496216773986816,
    "rear_shock_vel_p99_mps": 0.35235995054244995,
    "peak_lat_g": 3.663043260574341,
    "body_roll_p95_deg": 30.31,
    "body_roll_max_deg": -56.77350749564171,
    "roll_gradient_deg_per_g": -15.499,
    "lltd_measured": 0.5063948977100508,
    "understeer_mean_deg": 0.022944554686546326,
    "understeer_high_speed_deg": -0.029354136437177658,
    "understeer_low_speed_deg": 0.1562313288450241,
    "body_slip_p95_deg": 1.7357476949691772,
    "front_bottoming_events": 0,
    "rear_bottoming_events": 2,
    "front_heave_defl_p99_mm": 30.61,
    "front_heave_travel_used_pct": null,
    "front_heave_travel_used_braking_pct": null,
    "rear_heave_defl_p99_mm": null,
    "rear_heave_travel_used_pct": null,
    "heave_bottoming_events_front": 0,
    "heave_bottoming_events_rear": 0,
    "front_rh_settle_time_ms": 0.0,
    "rear_rh_settle_time_ms": 0.0,
    "front_dominant_freq_hz": 0.88,
    "rear_dominant_freq_hz": 0.88,
    "splitter_rh_mean_at_speed_mm": 42.67,
    "splitter_rh_min_mm": 25.13,
    "splitter_scrape_events": 0,
    "front_corner_defl_p99_mm": null,
    "rear_corner_defl_p99_mm": null,
    "front_heave_vel_p95_mps": 0.118,
    "rear_heave_vel_p95_mps": null,
    "front_heave_vel_ls_pct": 41.1,
    "front_heave_vel_hs_pct": 7.7,
    "lltd_low_speed": 0.5229817725798661,
    "lltd_high_speed": 0.4898948928664357,
    "measured_brake_bias_pct": 74.0,
    "abs_active_pct": 0.0,
    "abs_cut_mean_pct": 0.0,
    "brake_bias_adjustments": 0,
    "tc_adjustments": 0,
    "fuel_level_at_measurement_l": 47.2,
    "fuel_used_per_lap_l": 3.16,
    "ers_battery_mean_pct": 92.0,
    "ers_battery_min_pct": 80.0,
    "mguk_torque_peak_nm": 252.9,
    "air_temp_c": 18.9,
    "track_temp_c": 21.1,
    "air_density_kg_m3": 1.2008,
    "wind_speed_ms": 1.34,
    "wind_dir_deg": 225.0,
    "rpm_at_braking_pct_at_limiter": 0.0,
    "arb_front_adjustments": 0,
    "arb_rear_adjustments": 0,
    "front_brake_pressure_peak_bar": 97.0,
    "rear_brake_pressure_peak_bar": 93.7,
    "braking_decel_peak_g": 2.298,
    "tc_intervention_pct": 0.0,
    "pitch_mean_at_speed_deg": 0.218,
    "pitch_range_deg": 2.02,
    "pitch_range_braking_deg": 1.48,
    "front_rh_excursion_measured_mm": 24.61496353149414,
    "front_braking_lock_ratio_p95": 0.05492960661649704,
    "rear_power_slip_ratio_p95": 0.04818234220147133,
    "front_pressure_mean_kpa": 170.6,
    "rear_pressure_mean_kpa": 169.8,
    "understeer_left_turn_deg": -0.16397632658481598,
    "understeer_right_turn_deg": 0.5204719305038452,
    "lf_shock_vel_p95_mps": 0.12845811247825623,
    "rf_shock_vel_p95_mps": 0.13705582916736603,
    "lr_shock_vel_p95_mps": 0.19968989491462708,
    "rr_shock_vel_p95_mps": 0.22199121117591858,
    "lf_pressure_kpa": 168.0,
    "rf_pressure_kpa": 173.1,
    "lr_pressure_kpa": 167.3,
    "rr_pressure_kpa": 172.3,
    "lf_cold_pressure_kpa": 151.6,
    "rf_cold_pressure_kpa": 151.6,
    "lr_cold_pressure_kpa": 151.6,
    "rr_cold_pressure_kpa": 151.6,
    "lf_wear_pct": 100.0,
    "rf_wear_pct": 100.0,
    "lr_wear_pct": 100.0,
    "rr_wear_pct": 100.0,
    "lf_temp_middle_c": 41.9,
    "rf_temp_middle_c": 44.1,
    "lr_temp_middle_c": 47.3,
    "rr_temp_middle_c": 49.8,
    "rear_shock_oscillation_hz": 4.97,
    "front_shock_oscillation_hz": 9.34,
    "front_heave_vel_p95_hs_mps": 0.1076,
    "front_rh_std_hs_mm": 5.4256768226623535,
    "throttle_raw_mean": 0.75,
    "brake_raw_peak": 0.891,
    "gear_at_apex_mode": 0,
    "max_gear": 7,
    "tc2_adjustments": 0,
    "abs_adjustments": 0,
    "deploy_mode_adjustments": 0,
    "live_brake_bias_pct": 47.0,
    "live_tc_gain": 5,
    "live_tc_slip": 5,
    "live_front_arb_blade": 1,
    "live_rear_arb_blade": 3
  },
  "driver_profile": {
    "style": "smooth-consistent",
    "trail_braking_depth": 0.13522222222222224,
    "trail_braking_p95": 0.427,
    "trail_braking_class": "light",
    "brake_release_quality": 0.40910253132191254,
    "throttle_progressiveness": 0.6099399260562995,
    "throttle_onset_rate_pct_per_s": 18.103502888018344,
    "throttle_onset_aggression": 0.04525875722004586,
    "throttle_classification": "moderate",
    "steering_smoothness": "smooth",
    "steering_jerk_p95_rad_per_s2": 20.92325782775879,
    "apex_speed_cv": 0.0029883550819082127,
    "driver_noise_index": 0.0239068406552657,
    "classification_confidence": 0.661,
    "consistency": "consistent",
    "cornering_aggression": "limit",
    "avg_peak_lat_g_utilization": 59.1365565867307
  },
  "diagnosis": {
    "assessment": "competitive",
    "problem_count": 6,
    "evidence_strength": 0.656,
    "overhaul_assessment": {
      "classification": "moderate_rework",
      "confidence": 0.76,
      "score": 1.909,
      "reasons": [
        "Major states: thermal_window_invalid (1.00/0.85), front_contact_patch_undercambered (1.00/0.85)",
        "Impacted solver steps: 1, 2, 3, 5, 6",
        "State issues span multiple subsystems; more than a single tweak is required."
      ]
    },
    "state_issues": [
      {
        "state_id": "thermal_window_invalid",
        "severity": 1.0,
        "confidence": 0.85,
        "estimated_loss_ms": 291.5,
        "implicated_steps": [
          5
        ],
        "likely_causes": [
          "tyres operating outside thermal/pressure target window",
          "contact patch efficiency reduced"
        ],
        "recommended_direction": "move thermal state back toward target window before fine-tuning balance"
      },
      {
        "state_id": "front_contact_patch_undercambered",
        "severity": 1.0,
        "confidence": 0.85,
        "estimated_loss_ms": 110.0,
        "implicated_steps": [
          5
        ],
        "likely_causes": [
          "insufficient front negative camber",
          "front tyre contact patch too flat under load"
        ],
        "recommended_direction": "increase front negative camber or reduce front outer-shoulder overload"
      },
      {
        "state_id": "front_platform_near_limit_high_speed",
        "severity": 0.523,
        "confidence": 0.637,
        "estimated_loss_ms": 163.6,
        "implicated_steps": [
          1,
          2,
          6
        ],
        "likely_causes": [
          "front heave support too soft",
          "insufficient front ride-height margin",
          "HS damping not controlling aero events"
        ],
        "recommended_direction": "increase high-speed front platform support"
      },
      {
        "state_id": "balance_asymmetric",
        "severity": 0.456,
        "confidence": 0.7,
        "estimated_loss_ms": 62.4,
        "implicated_steps": [
          5
        ],
        "likely_causes": [
          "left/right tyre support imbalance",
          "camber or toe asymmetry interacting with track direction mix"
        ],
        "recommended_direction": "check directional balance and geometry asymmetry before global balance changes"
      },
      {
        "state_id": "rear_platform_under_supported",
        "severity": 0.34,
        "confidence": 0.637,
        "estimated_loss_ms": 121.0,
        "implicated_steps": [
          2,
          3,
          6
        ],
        "likely_causes": [
          "rear third spring too soft",
          "rear spring support too low",
          "rear HS damping too soft"
        ],
        "recommended_direction": "increase rear platform support"
      },
      {
        "state_id": "front_platform_collapse_braking",
        "severity": 0.725,
        "confidence": 0.262,
        "estimated_loss_ms": 191.5,
        "implicated_steps": [
          2,
          6
        ],
        "likely_causes": [
          "front heave spring too soft",
          "front heave perch consuming travel",
          "front LS damping mismatch"
        ],
        "recommended_direction": "increase front heave support and preserve braking travel margin"
      }
    ],
    "problems": [
      {
        "category": "platform",
        "severity": "significant",
        "symptom": "Braking pitch range 1.48 deg (mean +0.44 deg)",
        "measured": 1.48,
        "threshold": 0.9,
        "speed_context": "braking"
      },
      {
        "category": "balance",
        "severity": "minor",
        "symptom": "Directional balance asymmetry 0.68\u00b0 (left=-0.16\u00b0, right=+0.52\u00b0)",
        "measured": 0.6844482570886612,
        "threshold": 0.3,
        "speed_context": "cornering"
      },
      {
        "category": "thermal",
        "severity": "minor",
        "symptom": "RF spread +1.8C vs target +10C (too flat / outer loaded)",
        "measured": -8.2,
        "threshold": 6.8,
        "speed_context": "all"
      },
      {
        "category": "thermal",
        "severity": "minor",
        "symptom": "Front carcass temp 34C (target >80C)",
        "measured": 34.5,
        "threshold": 80.0,
        "speed_context": "all"
      },
      {
        "category": "thermal",
        "severity": "minor",
        "symptom": "Rear carcass temp 34C (target >80C)",
        "measured": 34.5,
        "threshold": 80.0,
        "speed_context": "all"
      },
      {
        "category": "grip",
        "severity": "minor",
        "symptom": "Hydraulic brake split 74.0% differs from setup 47.0% (delta 27.0%)",
        "measured": 74.0,
        "threshold": 47.0,
        "speed_context": "braking"
      }
    ]
  },
  "conditions": {
    "telemetry_source": "acuraarx06gtp_daytona 2011 road 2026-04-03 20-31-55.ibt \u2014 best lap 94.936s"
  },
  "solver_predictions": {
    "front_rh_std_mm": 0.0,
    "rear_rh_std_mm": 0.0,
    "lltd_predicted": 0.5254,
    "body_roll_predicted_deg_per_g": 0.0,
    "front_bottoming_predicted": 0,
    "front_heave_travel_used_pct": null,
    "front_excursion_mm": 26.008,
    "braking_pitch_deg": 1.595,
    "front_lock_p95": 0.0571,
    "rear_power_slip_p95": 0.0617,
    "body_slip_p95_deg": 1.775,
    "understeer_low_deg": 0.569,
    "understeer_high_deg": 0.249,
    "front_pressure_hot_kpa": 170.1,
    "rear_pressure_hot_kpa": 169.2
  },
  "solver_comparison": {},
  "validation_failed": false,
  "setup_fingerprint": "",
  "corner_performance": [
    {
      "corner_id": 0,
      "lap_dist_m": 0.2,
      "direction": "right",
      "speed_class": "low",
      "speed_kph": 83.5,
      "understeer_deg": 0.06,
      "body_slip_deg": 3.1,
      "braking_phase_s": 0.0,
      "release_phase_s": 0.0,
      "turn_in_phase_s": 18.633,
      "apex_phase_s": 0.233,
      "throttle_pickup_phase_s": 0.0,
      "exit_phase_s": 4.8,
      "corner_confidence": 0.75,
      "entry_pitch_severity": 0.294,
      "aero_collapse_severity": 1.238,
      "exit_slip_severity": 0.2
    },
    {
      "corner_id": 1,
      "lap_dist_m": 1149.8,
      "direction": "right",
      "speed_class": "high",
      "speed_kph": 197.1,
      "understeer_deg": 0.01,
      "body_slip_deg": 0.09,
      "braking_phase_s": 2.633,
      "release_phase_s": 0.0,
      "turn_in_phase_s": 0.0,
      "apex_phase_s": 0.117,
      "throttle_pickup_phase_s": 0.0,
      "exit_phase_s": 0.733,
      "corner_confidence": 0.85,
      "entry_pitch_severity": 0.0,
      "aero_collapse_severity": 0.198,
      "exit_slip_severity": 0.0
    },
    {
      "corner_id": 2,
      "lap_dist_m": 1231.6,
      "direction": "left",
      "speed_class": "low",
      "speed_kph": 93.0,
      "understeer_deg": 0.01,
      "body_slip_deg": 4.4,
      "braking_phase_s": 2.633,
      "release_phase_s": 9.333,
      "turn_in_phase_s": 0.0,
      "apex_phase_s": 0.233,
      "throttle_pickup_phase_s": 0.0,
      "exit_phase_s": 28.767,
      "corner_confidence": 0.85,
      "entry_pitch_severity": 0.246,
      "aero_collapse_severity": 1.294,
      "exit_slip_severity": 0.633
    },
    {
      "corner_id": 3,
      "lap_dist_m": 3551.8,
      "direction": "right",
      "speed_class": "high",
      "speed_kph": 315.4,
      "understeer_deg": 0.0,
      "body_slip_deg": 0.11,
      "braking_phase_s": 0.267,
      "release_phase_s": 0.0,
      "turn_in_phase_s": 0.0,
      "apex_phase_s": 0.083,
      "throttle_pickup_phase_s": 0.0,
      "exit_phase_s": 0.467,
      "corner_confidence": 0.75,
      "entry_pitch_severity": 0.0,
      "aero_collapse_severity": 0.0,
      "exit_slip_severity": 0.0
    },
    {
      "corner_id": 4,
      "lap_dist_m": 3610.3,
      "direction": "right",
      "speed_class": "high",
      "speed_kph": 316.4,
      "understeer_deg": 0.01,
      "body_slip_deg": 0.06,
      "braking_phase_s": 0.017,
      "release_phase_s": 0.0,
      "turn_in_phase_s": 0.0,
      "apex_phase_s": 0.033,
      "throttle_pickup_phase_s": 0.0,
      "exit_phase_s": 0.217,
      "corner_confidence": 0.65,
      "entry_pitch_severity": 0.0,
      "aero_collapse_severity": 0.0,
      "exit_slip_severity": 0.0
    },
    {
      "corner_id": 5,
      "lap_dist_m": 3714.4,
      "direction": "left",
      "speed_class": "mid",
      "speed_kph": 154.5,
      "understeer_deg": -0.03,
      "body_slip_deg": 3.8,
      "braking_phase_s": 2.133,
      "release_phase_s": 2.4,
      "turn_in_phase_s": 1.067,
      "apex_phase_s": 0.233,
      "throttle_pickup_phase_s": 0.0,
      "exit_phase_s": 17.95,
      "corner_confidence": 0.85,
      "entry_pitch_severity": 0.394,
      "aero_collapse_severity": 1.909,
      "exit_slip_severity": 0.435
    },
    {
      "corner_id": 6,
      "lap_dist_m": 5183.3,
      "direction": "right",
      "speed_class": "high",
      "speed_kph": 311.4,
      "understeer_deg": 0.0,
      "body_slip_deg": 0.08,
      "braking_phase_s": 2.133,
      "release_phase_s": 0.0,
      "turn_in_phase_s": 0.0,
      "apex_phase_s": 0.117,
      "throttle_pickup_phase_s": 0.0,
      "exit_phase_s": 0.633,
      "corner_confidence": 0.75,
      "entry_pitch_severity": 0.0,
      "aero_collapse_severity": 0.0,
      "exit_slip_severity": 0.0
    },
    {
      "corner_id": 7,
      "lap_dist_m": 5258.5,
      "direction": "right",
      "speed_class": "high",
      "speed_kph": 313.4,
      "understeer_deg": 0.0,
      "body_slip_deg": 0.06,
      "braking_phase_s": 2.133,
      "release_phase_s": 0.0,
      "turn_in_phase_s": 0.0,
      "apex_phase_s": 0.05,
      "throttle_pickup_phase_s": 0.0,
      "exit_phase_s": 0.317,
      "corner_confidence": 0.75,
      "entry_pitch_severity": 0.0,
      "aero_collapse_severity": 0.0,
      "exit_slip_severity": 0.0
    },
    {
      "corner_id": 8,
      "lap_dist_m": 5417.4,
      "direction": "left",
      "speed_class": "high",
      "speed_kph": 316.0,
      "understeer_deg": -0.01,
      "body_slip_deg": 0.33,
      "braking_phase_s": 2.133,
      "release_phase_s": 0.0,
      "turn_in_phase_s": 0.0,
      "apex_phase_s": 0.117,
      "throttle_pickup_phase_s": 0.0,
      "exit_phase_s": 2.95,
      "corner_confidence": 0.85,
      "entry_pitch_severity": 0.0,
      "aero_collapse_severity": 0.0,
      "exit_slip_severity": 0.0
    }
  ]
}