{
  "session_id": "acura_hockenheimring_baden-w\u00fcrttemberg_acuraarx06gtp_hockenheim_gp_2026-03-30_15-35-40",
  "ibt_path": "ibtfiles\\acuraarx06gtp_hockenheim gp 2026-03-30 15-35-40.ibt",
  "car": "acura",
  "track": "Hockenheimring Baden-W\u00fcrttemberg",
  "track_config": "Grand Prix",
  "timestamp": "2026-04-04T02:57:01.157524+00:00",
  "ibt_date": "",
  "setup": {
    "wing": 10.0,
    "adapter_name": "acura",
    "fuel_l": 58.0,
    "fuel_low_warning_l": 5.0,
    "fuel_target_l": 0.0,
    "front_rh_static": 30.1,
    "rear_rh_static": 46.1,
    "front_pushrod": -37.0,
    "rear_pushrod": -28.0,
    "front_heave_nmm": 230.0,
    "rear_third_nmm": 60.0,
    "torsion_bar_od_mm": 15.86,
    "rear_spring_nmm": 0.0,
    "front_heave_index": 230.0,
    "rear_heave_index": 60.0,
    "front_torsion_bar_index": 15.86,
    "rear_torsion_bar_index": 0.0,
    "front_arb_size": "Medium",
    "front_arb_blade": 1,
    "rear_arb_size": "Medium",
    "rear_arb_blade": 5,
    "front_camber_deg": -1.7,
    "rear_camber_deg": -1.4,
    "front_toe_mm": -0.5,
    "rear_toe_mm": 0.0,
    "brake_bias_pct": 47.0,
    "brake_bias_target": 0.0,
    "brake_bias_migration": 0.0,
    "brake_bias_migration_gain": 0.0,
    "front_master_cyl_mm": 20.6,
    "rear_master_cyl_mm": 22.2,
    "pad_compound": "Medium",
    "front_diff_preload_nm": 0.0,
    "diff_preload_nm": 30.0,
    "diff_ramp_label": "40/65",
    "diff_clutch_plates": 4,
    "tc_gain": 6,
    "tc_slip": 4,
    "gear_stack": "Short",
    "speed_in_first_kph": 131.1,
    "speed_in_second_kph": 163.4,
    "speed_in_third_kph": 191.0,
    "speed_in_fourth_kph": 220.3,
    "speed_in_fifth_kph": 249.6,
    "speed_in_sixth_kph": 283.1,
    "speed_in_seventh_kph": 320.2,
    "hybrid_rear_drive_enabled": "",
    "hybrid_rear_drive_corner_pct": 0.0,
    "roof_light_color": "Purple",
    "dampers": {
      "lf": {
        "ls_comp": 10,
        "ls_rbd": 10,
        "hs_comp": 8,
        "hs_rbd": 10,
        "hs_slope": 10
      },
      "rf": {
        "ls_comp": 10,
        "ls_rbd": 10,
        "hs_comp": 8,
        "hs_rbd": 10,
        "hs_slope": 10
      },
      "lr": {
        "ls_comp": 4,
        "ls_rbd": 5,
        "hs_comp": 4,
        "hs_rbd": 10,
        "hs_slope": 10
      },
      "rr": {
        "ls_comp": 4,
        "ls_rbd": 5,
        "hs_comp": 4,
        "hs_rbd": 10,
        "hs_slope": 10
      }
    },
    "roll_dampers": {
      "front": {
        "ls": 2,
        "hs": 3
      },
      "rear": {
        "ls": 9,
        "hs": 6
      }
    },
    "rear_torsion_od_mm": 14.34
  },
  "performance": {
    "best_lap_time_s": 88.04753112792969,
    "lap_number": 14,
    "median_speed_kph": 188.9,
    "max_speed_kph": 303.5,
    "consistency_cv": 0.11206519927500774
  },
  "telemetry": {
    "dynamic_front_rh_mm": 22.02231216430664,
    "dynamic_rear_rh_mm": 23.59872817993164,
    "front_rh_std_mm": 4.8375959396362305,
    "rear_rh_std_mm": 7.610132694244385,
    "front_shock_vel_p95_mps": 0.1545712798833847,
    "rear_shock_vel_p95_mps": 0.21615751087665558,
    "front_shock_vel_p99_mps": 0.3301677405834198,
    "rear_shock_vel_p99_mps": 0.4601442515850067,
    "peak_lat_g": 4.569421291351318,
    "body_roll_p95_deg": 2.78,
    "body_roll_max_deg": 2.065378423690796,
    "roll_gradient_deg_per_g": 0.452,
    "lltd_measured": 0.5106550634818139,
    "understeer_mean_deg": -0.007096233777701855,
    "understeer_high_speed_deg": -0.1748686283826828,
    "understeer_low_speed_deg": 0.3942948877811432,
    "body_slip_p95_deg": 2.6419734954833984,
    "front_bottoming_events": 6,
    "rear_bottoming_events": 1,
    "front_heave_defl_p99_mm": 21.78,
    "front_heave_travel_used_pct": null,
    "front_heave_travel_used_braking_pct": null,
    "rear_heave_defl_p99_mm": null,
    "rear_heave_travel_used_pct": null,
    "heave_bottoming_events_front": 0,
    "heave_bottoming_events_rear": 0,
    "front_rh_settle_time_ms": 0.0,
    "rear_rh_settle_time_ms": 0.0,
    "front_dominant_freq_hz": 0.94,
    "rear_dominant_freq_hz": 0.94,
    "splitter_rh_mean_at_speed_mm": 47.89,
    "splitter_rh_min_mm": 16.54,
    "splitter_scrape_events": 0,
    "front_corner_defl_p99_mm": null,
    "rear_corner_defl_p99_mm": null,
    "front_heave_vel_p95_mps": 0.1449,
    "rear_heave_vel_p95_mps": null,
    "front_heave_vel_ls_pct": 49.2,
    "front_heave_vel_hs_pct": 8.8,
    "lltd_low_speed": 0.5089658288240114,
    "lltd_high_speed": 0.5063586258226589,
    "measured_brake_bias_pct": 72.4,
    "abs_active_pct": 0.0,
    "abs_cut_mean_pct": 0.0,
    "brake_bias_adjustments": 0,
    "tc_adjustments": 0,
    "fuel_level_at_measurement_l": 46.4,
    "fuel_used_per_lap_l": 2.63,
    "ers_battery_mean_pct": 55.8,
    "ers_battery_min_pct": 48.3,
    "mguk_torque_peak_nm": 302.2,
    "air_temp_c": 18.3,
    "track_temp_c": 22.8,
    "air_density_kg_m3": 1.1923,
    "wind_speed_ms": 4.02,
    "wind_dir_deg": 270.0,
    "rpm_at_braking_pct_at_limiter": 0.0,
    "arb_front_adjustments": 0,
    "arb_rear_adjustments": 8,
    "front_brake_pressure_peak_bar": 108.9,
    "rear_brake_pressure_peak_bar": 99.6,
    "braking_decel_peak_g": 2.504,
    "tc_intervention_pct": 0.0,
    "pitch_mean_at_speed_deg": 0.05,
    "pitch_range_deg": 2.57,
    "pitch_range_braking_deg": 2.32,
    "front_rh_excursion_measured_mm": 34.54068374633789,
    "front_braking_lock_ratio_p95": 0.10178141295909882,
    "rear_power_slip_ratio_p95": 0.09391707181930542,
    "front_pressure_mean_kpa": 173.5,
    "rear_pressure_mean_kpa": 170.2,
    "understeer_left_turn_deg": -0.32398170232772827,
    "understeer_right_turn_deg": 0.2037491649389267,
    "lf_shock_vel_p95_mps": 0.16923978924751282,
    "rf_shock_vel_p95_mps": 0.141374871134758,
    "lr_shock_vel_p95_mps": 0.21920770406723022,
    "rr_shock_vel_p95_mps": 0.21173381805419922,
    "lf_pressure_kpa": 175.5,
    "rf_pressure_kpa": 171.5,
    "lr_pressure_kpa": 171.2,
    "rr_pressure_kpa": 169.1,
    "lf_cold_pressure_kpa": 151.6,
    "rf_cold_pressure_kpa": 151.6,
    "lr_cold_pressure_kpa": 151.6,
    "rr_cold_pressure_kpa": 151.6,
    "lf_wear_pct": 96.3,
    "rf_wear_pct": 97.8,
    "lr_wear_pct": 95.6,
    "rr_wear_pct": 96.4,
    "lf_temp_middle_c": 53.9,
    "rf_temp_middle_c": 49.8,
    "lr_temp_middle_c": 56.9,
    "rr_temp_middle_c": 55.2,
    "rear_shock_oscillation_hz": 7.92,
    "front_shock_oscillation_hz": 11.19,
    "front_heave_vel_p95_hs_mps": 0.1366,
    "front_rh_std_hs_mm": 4.9409966468811035,
    "throttle_raw_mean": 0.709,
    "brake_raw_peak": 1.0,
    "gear_at_apex_mode": 0,
    "max_gear": 7,
    "tc2_adjustments": 0,
    "abs_adjustments": 0,
    "deploy_mode_adjustments": 0,
    "live_brake_bias_pct": 47.0,
    "live_tc_gain": 4,
    "live_tc_slip": 6,
    "live_front_arb_blade": 1,
    "live_rear_arb_blade": null
  },
  "driver_profile": {
    "style": "aggressive-erratic",
    "trail_braking_depth": 0.30906249999999996,
    "trail_braking_p95": 1.0,
    "trail_braking_class": "moderate",
    "brake_release_quality": 0.0,
    "throttle_progressiveness": 0.529952931569333,
    "throttle_onset_rate_pct_per_s": 72.02717127199304,
    "throttle_onset_aggression": 0.1800679281799826,
    "throttle_classification": "moderate",
    "steering_smoothness": "smooth",
    "steering_jerk_p95_rad_per_s2": 27.024005889892578,
    "apex_speed_cv": 0.11206519927500774,
    "driver_noise_index": 0.8965215942000619,
    "classification_confidence": 0.399,
    "consistency": "erratic",
    "cornering_aggression": "limit",
    "avg_peak_lat_g_utilization": 30.56335028646072
  },
  "diagnosis": {
    "assessment": "compromised",
    "problem_count": 10,
    "evidence_strength": 0.608,
    "overhaul_assessment": {
      "classification": "moderate_rework",
      "confidence": 0.76,
      "score": 2.07,
      "reasons": [
        "Major states: front_contact_patch_undercambered (1.00/0.85)",
        "Impacted solver steps: 2, 3, 4, 5, 6",
        "State issues span multiple subsystems; more than a single tweak is required."
      ]
    },
    "state_issues": [
      {
        "state_id": "front_contact_patch_undercambered",
        "severity": 1.0,
        "confidence": 0.85,
        "estimated_loss_ms": 110.0,
        "implicated_steps": [
          5
        ],
        "likely_causes": [
          "insufficient front negative camber",
          "front tyre contact patch too flat under load"
        ],
        "recommended_direction": "increase front negative camber or reduce front outer-shoulder overload"
      },
      {
        "state_id": "brake_system_front_limited",
        "severity": 0.836,
        "confidence": 0.587,
        "estimated_loss_ms": 134.4,
        "implicated_steps": [
          6
        ],
        "likely_causes": [
          "front brake demand exceeds tyre support",
          "bias too far forward",
          "entry platform collapsing into front lock"
        ],
        "recommended_direction": "reduce front brake limitation before chasing corner-entry rotation"
      },
      {
        "state_id": "front_platform_collapse_braking",
        "severity": 1.0,
        "confidence": 0.262,
        "estimated_loss_ms": 338.5,
        "implicated_steps": [
          2,
          6
        ],
        "likely_causes": [
          "front heave spring too soft",
          "front heave perch consuming travel",
          "front LS damping mismatch"
        ],
        "recommended_direction": "increase front heave support and preserve braking travel margin"
      },
      {
        "state_id": "balance_asymmetric",
        "severity": 0.352,
        "confidence": 0.7,
        "estimated_loss_ms": 56.1,
        "implicated_steps": [
          5
        ],
        "likely_causes": [
          "left/right tyre support imbalance",
          "camber or toe asymmetry interacting with track direction mix"
        ],
        "recommended_direction": "check directional balance and geometry asymmetry before global balance changes"
      },
      {
        "state_id": "exit_traction_limited",
        "severity": 0.232,
        "confidence": 0.615,
        "estimated_loss_ms": 110.2,
        "implicated_steps": [
          3,
          4,
          6
        ],
        "likely_causes": [
          "rear support not matching traction demand",
          "diff/TC too aggressive or too open",
          "rear contact patch overloaded on exit"
        ],
        "recommended_direction": "increase exit traction support and rear stability"
      },
      {
        "state_id": "rear_platform_under_supported",
        "severity": 0.122,
        "confidence": 0.637,
        "estimated_loss_ms": 88.3,
        "implicated_steps": [
          2,
          3,
          6
        ],
        "likely_causes": [
          "rear third spring too soft",
          "rear spring support too low",
          "rear HS damping too soft"
        ],
        "recommended_direction": "increase rear platform support"
      }
    ],
    "problems": [
      {
        "category": "safety",
        "severity": "minor",
        "symptom": "6 front bottoming events on kerbs only",
        "measured": 6.0,
        "threshold": 6.0,
        "speed_context": "all"
      },
      {
        "category": "safety",
        "severity": "minor",
        "symptom": "1 rear bottoming events on kerbs only",
        "measured": 1.0,
        "threshold": 6.0,
        "speed_context": "all"
      },
      {
        "category": "platform",
        "severity": "significant",
        "symptom": "Front excursion p99 34.5mm = 150% of dynamic RH (23mm)",
        "measured": 150.176885853643,
        "threshold": 80.0,
        "speed_context": "high"
      },
      {
        "category": "platform",
        "severity": "significant",
        "symptom": "Braking pitch range 2.32 deg (mean -0.00 deg)",
        "measured": 2.32,
        "threshold": 0.9,
        "speed_context": "braking"
      },
      {
        "category": "balance",
        "severity": "minor",
        "symptom": "Directional balance asymmetry 0.53\u00b0 (left=-0.32\u00b0, right=+0.20\u00b0)",
        "measured": 0.527730867266655,
        "threshold": 0.3,
        "speed_context": "cornering"
      },
      {
        "category": "thermal",
        "severity": "significant",
        "symptom": "LF spread -0.8C vs target +10C (too flat / outer loaded)",
        "measured": -10.8,
        "threshold": 4.8,
        "speed_context": "all"
      },
      {
        "category": "thermal",
        "severity": "minor",
        "symptom": "RF spread +4.2C vs target +10C (too flat / outer loaded)",
        "measured": -5.8,
        "threshold": 4.8,
        "speed_context": "all"
      },
      {
        "category": "grip",
        "severity": "significant",
        "symptom": "Front braking slip p95 = 0.102 (target <0.06)",
        "measured": 0.10178141295909882,
        "threshold": 0.06,
        "speed_context": "braking"
      },
      {
        "category": "grip",
        "severity": "minor",
        "symptom": "Rear traction slip p95 = 0.094 (target <0.08)",
        "measured": 0.09391707181930542,
        "threshold": 0.08,
        "speed_context": "traction"
      },
      {
        "category": "grip",
        "severity": "minor",
        "symptom": "Hydraulic brake split 72.4% differs from setup 47.0% (delta 25.4%)",
        "measured": 72.4,
        "threshold": 47.0,
        "speed_context": "braking"
      }
    ]
  },
  "conditions": {
    "telemetry_source": "acuraarx06gtp_hockenheim gp 2026-03-30 15-35-40.ibt \u2014 best lap 88.048s"
  },
  "solver_predictions": {
    "front_rh_std_mm": 0.0,
    "rear_rh_std_mm": 0.0,
    "lltd_predicted": 0.5369,
    "body_roll_predicted_deg_per_g": 0.0,
    "front_bottoming_predicted": 0,
    "front_heave_travel_used_pct": null,
    "front_excursion_mm": 43.176,
    "braking_pitch_deg": 2.9,
    "front_lock_p95": 0.1253,
    "rear_power_slip_p95": 0.0879,
    "body_slip_p95_deg": 2.437,
    "understeer_low_deg": 0.41,
    "understeer_high_deg": -0.14,
    "front_pressure_hot_kpa": 173.65,
    "rear_pressure_hot_kpa": 170.65
  },
  "solver_comparison": {},
  "validation_failed": false,
  "setup_fingerprint": "",
  "corner_performance": [
    {
      "corner_id": 0,
      "lap_dist_m": 81.9,
      "direction": "right",
      "speed_class": "high",
      "speed_kph": 185.9,
      "understeer_deg": -0.18,
      "body_slip_deg": 4.08,
      "braking_phase_s": 1.483,
      "release_phase_s": 0.533,
      "turn_in_phase_s": 2.45,
      "apex_phase_s": 0.233,
      "throttle_pickup_phase_s": 0.0,
      "exit_phase_s": 4.183,
      "corner_confidence": 0.85,
      "entry_pitch_severity": 0.539,
      "aero_collapse_severity": 2.165,
      "exit_slip_severity": 0.527
    },
    {
      "corner_id": 1,
      "lap_dist_m": 557.6,
      "direction": "right",
      "speed_class": "high",
      "speed_kph": 252.3,
      "understeer_deg": -0.0,
      "body_slip_deg": 0.03,
      "braking_phase_s": 1.483,
      "release_phase_s": 0.0,
      "turn_in_phase_s": 0.0,
      "apex_phase_s": 0.05,
      "throttle_pickup_phase_s": 0.0,
      "exit_phase_s": 0.3,
      "corner_confidence": 0.75,
      "entry_pitch_severity": 0.0,
      "aero_collapse_severity": 0.0,
      "exit_slip_severity": 0.0
    },
    {
      "corner_id": 2,
      "lap_dist_m": 611.0,
      "direction": "left",
      "speed_class": "high",
      "speed_kph": 260.2,
      "understeer_deg": 0.01,
      "body_slip_deg": 0.08,
      "braking_phase_s": 0.0,
      "release_phase_s": 0.0,
      "turn_in_phase_s": 0.0,
      "apex_phase_s": 0.1,
      "throttle_pickup_phase_s": 0.0,
      "exit_phase_s": 0.55,
      "corner_confidence": 0.75,
      "entry_pitch_severity": 0.0,
      "aero_collapse_severity": 0.0,
      "exit_slip_severity": 0.0
    },
    {
      "corner_id": 3,
      "lap_dist_m": 690.4,
      "direction": "left",
      "speed_class": "high",
      "speed_kph": 225.0,
      "understeer_deg": 0.0,
      "body_slip_deg": 0.05,
      "braking_phase_s": 0.667,
      "release_phase_s": 0.0,
      "turn_in_phase_s": 0.35,
      "apex_phase_s": 0.067,
      "throttle_pickup_phase_s": 0.0,
      "exit_phase_s": 0.0,
      "corner_confidence": 0.75,
      "entry_pitch_severity": 1.5,
      "aero_collapse_severity": 0.0,
      "exit_slip_severity": 0.0
    },
    {
      "corner_id": 4,
      "lap_dist_m": 773.7,
      "direction": "right",
      "speed_class": "low",
      "speed_kph": 82.5,
      "understeer_deg": 0.17,
      "body_slip_deg": 3.34,
      "braking_phase_s": 2.967,
      "release_phase_s": 1.183,
      "turn_in_phase_s": 1.117,
      "apex_phase_s": 0.233,
      "throttle_pickup_phase_s": 0.0,
      "exit_phase_s": 6.95,
      "corner_confidence": 0.85,
      "entry_pitch_severity": 0.645,
      "aero_collapse_severity": 1.31,
      "exit_slip_severity": 0.279
    },
    {
      "corner_id": 5,
      "lap_dist_m": 1168.5,
      "direction": "right",
      "speed_class": "high",
      "speed_kph": 235.2,
      "understeer_deg": -0.01,
      "body_slip_deg": 0.04,
      "braking_phase_s": 2.967,
      "release_phase_s": 0.0,
      "turn_in_phase_s": 0.0,
      "apex_phase_s": 0.017,
      "throttle_pickup_phase_s": 0.0,
      "exit_phase_s": 0.15,
      "corner_confidence": 0.55,
      "entry_pitch_severity": 0.0,
      "aero_collapse_severity": 0.0,
      "exit_slip_severity": 0.0
    },
    {
      "corner_id": 6,
      "lap_dist_m": 1192.8,
      "direction": "left",
      "speed_class": "high",
      "speed_kph": 240.5,
      "understeer_deg": 0.02,
      "body_slip_deg": 0.56,
      "braking_phase_s": 2.967,
      "release_phase_s": 0.0,
      "turn_in_phase_s": 0.0,
      "apex_phase_s": 0.117,
      "throttle_pickup_phase_s": 0.0,
      "exit_phase_s": 7.117,
      "corner_confidence": 0.85,
      "entry_pitch_severity": 0.0,
      "aero_collapse_severity": 0.119,
      "exit_slip_severity": 0.0
    },
    {
      "corner_id": 7,
      "lap_dist_m": 1769.0,
      "direction": "left",
      "speed_class": "high",
      "speed_kph": 297.3,
      "understeer_deg": 0.0,
      "body_slip_deg": 0.04,
      "braking_phase_s": 2.967,
      "release_phase_s": 0.0,
      "turn_in_phase_s": 0.0,
      "apex_phase_s": 0.117,
      "throttle_pickup_phase_s": 0.0,
      "exit_phase_s": 1.05,
      "corner_confidence": 0.85,
      "entry_pitch_severity": 0.0,
      "aero_collapse_severity": 0.0,
      "exit_slip_severity": 0.0
    },
    {
      "corner_id": 8,
      "lap_dist_m": 1921.5,
      "direction": "right",
      "speed_class": "high",
      "speed_kph": 257.1,
      "understeer_deg": 0.01,
      "body_slip_deg": 0.06,
      "braking_phase_s": 0.583,
      "release_phase_s": 0.0,
      "turn_in_phase_s": 0.267,
      "apex_phase_s": 0.05,
      "throttle_pickup_phase_s": 0.0,
      "exit_phase_s": 0.0,
      "corner_confidence": 0.65,
      "entry_pitch_severity": 1.5,
      "aero_collapse_severity": 0.0,
      "exit_slip_severity": 0.0
    },
    {
      "corner_id": 9,
      "lap_dist_m": 1983.9,
      "direction": "right",
      "speed_class": "low",
      "speed_kph": 51.9,
      "understeer_deg": 1.2,
      "body_slip_deg": 2.96,
      "braking_phase_s": 4.267,
      "release_phase_s": 0.217,
      "turn_in_phase_s": 3.033,
      "apex_phase_s": 0.233,
      "throttle_pickup_phase_s": 0.0,
      "exit_phase_s": 3.4,
      "corner_confidence": 0.85,
      "entry_pitch_severity": 1.449,
      "aero_collapse_severity": 1.048,
      "exit_slip_severity": 0.155
    },
    {
      "corner_id": 10,
      "lap_dist_m": 2171.2,
      "direction": "left",
      "speed_class": "mid",
      "speed_kph": 140.2,
      "understeer_deg": -0.04,
      "body_slip_deg": 0.17,
      "braking_phase_s": 4.267,
      "release_phase_s": 0.0,
      "turn_in_phase_s": 0.0,
      "apex_phase_s": 0.117,
      "throttle_pickup_phase_s": 0.0,
      "exit_phase_s": 1.317,
      "corner_confidence": 0.85,
      "entry_pitch_severity": 0.0,
      "aero_collapse_severity": 0.0,
      "exit_slip_severity": 0.0
    },
    {
      "corner_id": 11,
      "lap_dist_m": 2239.5,
      "direction": "left",
      "speed_class": "high",
      "speed_kph": 182.0,
      "understeer_deg": -0.01,
      "body_slip_deg": 0.05,
      "braking_phase_s": 4.267,
      "release_phase_s": 0.0,
      "turn_in_phase_s": 0.0,
      "apex_phase_s": 0.067,
      "throttle_pickup_phase_s": 0.0,
      "exit_phase_s": 0.333,
      "corner_confidence": 0.75,
      "entry_pitch_severity": 0.0,
      "aero_collapse_severity": 0.0,
      "exit_slip_severity": 0.0
    },
    {
      "corner_id": 12,
      "lap_dist_m": 2316.9,
      "direction": "left",
      "speed_class": "high",
      "speed_kph": 210.7,
      "understeer_deg": -0.01,
      "body_slip_deg": 0.04,
      "braking_phase_s": 4.267,
      "release_phase_s": 0.0,
      "turn_in_phase_s": 0.0,
      "apex_phase_s": 0.017,
      "throttle_pickup_phase_s": 0.0,
      "exit_phase_s": 0.167,
      "corner_confidence": 0.55,
      "entry_pitch_severity": 0.0,
      "aero_collapse_severity": 0.0,
      "exit_slip_severity": 0.0
    },
    {
      "corner_id": 13,
      "lap_dist_m": 2344.7,
      "direction": "left",
      "speed_class": "low",
      "speed_kph": 91.7,
      "understeer_deg": -0.21,
      "body_slip_deg": 4.22,
      "braking_phase_s": 4.267,
      "release_phase_s": 8.217,
      "turn_in_phase_s": 0.0,
      "apex_phase_s": 0.233,
      "throttle_pickup_phase_s": 0.0,
      "exit_phase_s": 10.133,
      "corner_confidence": 0.85,
      "entry_pitch_severity": 0.433,
      "aero_collapse_severity": 2.075,
      "exit_slip_severity": 0.573
    },
    {
      "corner_id": 14,
      "lap_dist_m": 3297.8,
      "direction": "right",
      "speed_class": "low",
      "speed_kph": 101.5,
      "understeer_deg": -0.19,
      "body_slip_deg": 5.36,
      "braking_phase_s": 1.083,
      "release_phase_s": 8.417,
      "turn_in_phase_s": 1.017,
      "apex_phase_s": 0.233,
      "throttle_pickup_phase_s": 0.0,
      "exit_phase_s": 14.683,
      "corner_confidence": 0.85,
      "entry_pitch_severity": 0.323,
      "aero_collapse_severity": 2.251,
      "exit_slip_severity": 0.954
    },
    {
      "corner_id": 15,
      "lap_dist_m": 4402.2,
      "direction": "left",
      "speed_class": "high",
      "speed_kph": 207.5,
      "understeer_deg": -0.0,
      "body_slip_deg": 0.13,
      "braking_phase_s": 0.2,
      "release_phase_s": 0.0,
      "turn_in_phase_s": 0.0,
      "apex_phase_s": 0.117,
      "throttle_pickup_phase_s": 0.0,
      "exit_phase_s": 1.217,
      "corner_confidence": 0.85,
      "entry_pitch_severity": 0.0,
      "aero_collapse_severity": 0.0,
      "exit_slip_severity": 0.0
    }
  ]
}