{
  "session_before": "bmw_sebring_international_raceway_bmwlmdh_sebring_international_2026-03-11_20-24-34",
  "session_after": "bmw_sebring_international_raceway_bmwlmdh_sebring_international_2026-03-11_20-40-35",
  "car": "bmw",
  "track": "Sebring International Raceway",
  "setup_changes": [
    {
      "parameter": "rear_camber_deg",
      "before": -1.6,
      "after": -1.2,
      "delta": 0.40000000000000013,
      "step_group": "step5_geometry",
      "significance": "minor"
    },
    {
      "parameter": "front_toe_mm",
      "before": -0.4,
      "after": -0.5,
      "delta": -0.09999999999999998,
      "step_group": "step5_geometry",
      "significance": "trivial"
    },
    {
      "parameter": "rear_spring_nmm",
      "before": 140.0,
      "after": 180.0,
      "delta": 40.0,
      "step_group": "step3_springs",
      "significance": "major"
    },
    {
      "parameter": "rear_pushrod",
      "before": -31.0,
      "after": -30.0,
      "delta": 1.0,
      "step_group": "step1_rake",
      "significance": "minor"
    },
    {
      "parameter": "brake_bias_pct",
      "before": 45.25,
      "after": 45.5,
      "delta": 0.25,
      "step_group": "other",
      "significance": "trivial"
    },
    {
      "parameter": "rear_third_nmm",
      "before": 420.0,
      "after": 540.0,
      "delta": 120.0,
      "step_group": "step2_heave",
      "significance": "major"
    },
    {
      "parameter": "front_pushrod",
      "before": -25.5,
      "after": -26.5,
      "delta": -1.0,
      "step_group": "step1_rake",
      "significance": "minor"
    },
    {
      "parameter": "rear_rh_static",
      "before": 45.3,
      "after": 49.5,
      "delta": 4.200000000000003,
      "step_group": "step1_rake",
      "significance": "minor"
    },
    {
      "parameter": "rear_toe_mm",
      "before": -0.1,
      "after": -0.7,
      "delta": -0.6,
      "step_group": "step5_geometry",
      "significance": "major"
    },
    {
      "parameter": "damper_lr_ls_comp",
      "before": 5,
      "after": 6,
      "delta": 1,
      "step_group": "step6_dampers",
      "significance": "minor"
    },
    {
      "parameter": "damper_lr_ls_rbd",
      "before": 6,
      "after": 7,
      "delta": 1,
      "step_group": "step6_dampers",
      "significance": "minor"
    },
    {
      "parameter": "damper_rr_ls_comp",
      "before": 5,
      "after": 6,
      "delta": 1,
      "step_group": "step6_dampers",
      "significance": "minor"
    },
    {
      "parameter": "damper_rr_ls_rbd",
      "before": 6,
      "after": 7,
      "delta": 1,
      "step_group": "step6_dampers",
      "significance": "minor"
    }
  ],
  "telemetry_effects": [
    {
      "metric": "front_rh_std_mm",
      "category": "platform",
      "before": 6.046815395355225,
      "after": 5.364407539367676,
      "delta": -0.6824,
      "pct_change": -11.3,
      "significance": "moderate"
    },
    {
      "metric": "rear_rh_std_mm",
      "category": "platform",
      "before": 8.590513229370117,
      "after": 7.188198089599609,
      "delta": -1.4023,
      "pct_change": -16.3,
      "significance": "moderate"
    },
    {
      "metric": "rear_bottoming_events",
      "category": "platform",
      "before": 4.0,
      "after": 6.0,
      "delta": 2.0,
      "pct_change": 50.0,
      "significance": "moderate"
    },
    {
      "metric": "front_shock_vel_p95_mps",
      "category": "platform",
      "before": 0.13925570249557495,
      "after": 0.1320757269859314,
      "delta": -0.0072,
      "pct_change": -5.2,
      "significance": "moderate"
    },
    {
      "metric": "rear_shock_vel_p95_mps",
      "category": "platform",
      "before": 0.18245774507522583,
      "after": 0.16260917484760284,
      "delta": -0.0198,
      "pct_change": -10.9,
      "significance": "moderate"
    },
    {
      "metric": "understeer_high_speed_deg",
      "category": "balance",
      "before": 0.1629587709903717,
      "after": 0.10535717010498047,
      "delta": -0.0576,
      "pct_change": -35.3,
      "significance": "large"
    },
    {
      "metric": "understeer_low_speed_deg",
      "category": "balance",
      "before": -0.12701435387134552,
      "after": 0.02150418795645237,
      "delta": 0.1485,
      "pct_change": 116.9,
      "significance": "large"
    },
    {
      "metric": "dynamic_front_rh_mm",
      "category": "aero",
      "before": 22.342344284057617,
      "after": 21.792722702026367,
      "delta": -0.5496,
      "pct_change": -2.5,
      "significance": "small"
    },
    {
      "metric": "dynamic_rear_rh_mm",
      "category": "aero",
      "before": 22.450878143310547,
      "after": 30.21674919128418,
      "delta": 7.7659,
      "pct_change": 34.6,
      "significance": "large"
    }
  ],
  "hypotheses": [
    {
      "cause_param": "rear_camber_deg",
      "cause_delta": 0.40000000000000013,
      "effect_metric": "front_rh_std_mm",
      "effect_delta": -0.6824,
      "direction_match": false,
      "confidence": 0.1,
      "mechanism": "rear_camber_deg + -> observed front_rh_std_mm - (no known causal link)",
      "corroborated_by": 0
    },
    {
      "cause_param": "rear_camber_deg",
      "cause_delta": 0.40000000000000013,
      "effect_metric": "rear_rh_std_mm",
      "effect_delta": -1.4023,
      "direction_match": false,
      "confidence": 0.1,
      "mechanism": "rear_camber_deg + -> observed rear_rh_std_mm - (no known causal link)",
      "corroborated_by": 0
    },
    {
      "cause_param": "rear_camber_deg",
      "cause_delta": 0.40000000000000013,
      "effect_metric": "rear_bottoming_events",
      "effect_delta": 2.0,
      "direction_match": false,
      "confidence": 0.1,
      "mechanism": "rear_camber_deg + -> observed rear_bottoming_events + (no known causal link)",
      "corroborated_by": 0
    },
    {
      "cause_param": "rear_camber_deg",
      "cause_delta": 0.40000000000000013,
      "effect_metric": "front_shock_vel_p95_mps",
      "effect_delta": -0.0072,
      "direction_match": false,
      "confidence": 0.1,
      "mechanism": "rear_camber_deg + -> observed front_shock_vel_p95_mps - (no known causal link)",
      "corroborated_by": 0
    },
    {
      "cause_param": "rear_camber_deg",
      "cause_delta": 0.40000000000000013,
      "effect_metric": "rear_shock_vel_p95_mps",
      "effect_delta": -0.0198,
      "direction_match": false,
      "confidence": 0.1,
      "mechanism": "rear_camber_deg + -> observed rear_shock_vel_p95_mps - (no known causal link)",
      "corroborated_by": 0
    },
    {
      "cause_param": "rear_camber_deg",
      "cause_delta": 0.40000000000000013,
      "effect_metric": "understeer_high_speed_deg",
      "effect_delta": -0.0576,
      "direction_match": false,
      "confidence": 0.1,
      "mechanism": "rear_camber_deg + -> observed understeer_high_speed_deg - (no known causal link)",
      "corroborated_by": 0
    },
    {
      "cause_param": "rear_camber_deg",
      "cause_delta": 0.40000000000000013,
      "effect_metric": "understeer_low_speed_deg",
      "effect_delta": 0.1485,
      "direction_match": false,
      "confidence": 0.1,
      "mechanism": "rear_camber_deg + -> observed understeer_low_speed_deg + (no known causal link)",
      "corroborated_by": 0
    },
    {
      "cause_param": "rear_camber_deg",
      "cause_delta": 0.40000000000000013,
      "effect_metric": "dynamic_front_rh_mm",
      "effect_delta": -0.5496,
      "direction_match": false,
      "confidence": 0.1,
      "mechanism": "rear_camber_deg + -> observed dynamic_front_rh_mm - (no known causal link)",
      "corroborated_by": 0
    },
    {
      "cause_param": "rear_camber_deg",
      "cause_delta": 0.40000000000000013,
      "effect_metric": "dynamic_rear_rh_mm",
      "effect_delta": 7.7659,
      "direction_match": false,
      "confidence": 0.1,
      "mechanism": "rear_camber_deg + -> observed dynamic_rear_rh_mm + (no known causal link)",
      "corroborated_by": 0
    },
    {
      "cause_param": "rear_spring_nmm",
      "cause_delta": 40.0,
      "effect_metric": "front_rh_std_mm",
      "effect_delta": -0.6824,
      "direction_match": false,
      "confidence": 0.1,
      "mechanism": "rear_spring_nmm + -> observed front_rh_std_mm - (no known causal link)",
      "corroborated_by": 0
    },
    {
      "cause_param": "rear_spring_nmm",
      "cause_delta": 40.0,
      "effect_metric": "rear_rh_std_mm",
      "effect_delta": -1.4023,
      "direction_match": false,
      "confidence": 0.1,
      "mechanism": "rear_spring_nmm + -> observed rear_rh_std_mm - (no known causal link)",
      "corroborated_by": 0
    },
    {
      "cause_param": "rear_spring_nmm",
      "cause_delta": 40.0,
      "effect_metric": "rear_bottoming_events",
      "effect_delta": 2.0,
      "direction_match": false,
      "confidence": 0.1,
      "mechanism": "rear_spring_nmm + -> observed rear_bottoming_events + (no known causal link)",
      "corroborated_by": 0
    },
    {
      "cause_param": "rear_spring_nmm",
      "cause_delta": 40.0,
      "effect_metric": "front_shock_vel_p95_mps",
      "effect_delta": -0.0072,
      "direction_match": false,
      "confidence": 0.1,
      "mechanism": "rear_spring_nmm + -> observed front_shock_vel_p95_mps - (no known causal link)",
      "corroborated_by": 0
    },
    {
      "cause_param": "rear_spring_nmm",
      "cause_delta": 40.0,
      "effect_metric": "rear_shock_vel_p95_mps",
      "effect_delta": -0.0198,
      "direction_match": false,
      "confidence": 0.1,
      "mechanism": "rear_spring_nmm + -> observed rear_shock_vel_p95_mps - (no known causal link)",
      "corroborated_by": 0
    },
    {
      "cause_param": "rear_spring_nmm",
      "cause_delta": 40.0,
      "effect_metric": "understeer_high_speed_deg",
      "effect_delta": -0.0576,
      "direction_match": false,
      "confidence": 0.1,
      "mechanism": "rear_spring_nmm + -> observed understeer_high_speed_deg - (no known causal link)",
      "corroborated_by": 0
    },
    {
      "cause_param": "rear_spring_nmm",
      "cause_delta": 40.0,
      "effect_metric": "understeer_low_speed_deg",
      "effect_delta": 0.1485,
      "direction_match": false,
      "confidence": 0.1,
      "mechanism": "rear_spring_nmm + -> observed understeer_low_speed_deg + (no known causal link)",
      "corroborated_by": 0
    },
    {
      "cause_param": "rear_spring_nmm",
      "cause_delta": 40.0,
      "effect_metric": "dynamic_front_rh_mm",
      "effect_delta": -0.5496,
      "direction_match": false,
      "confidence": 0.1,
      "mechanism": "rear_spring_nmm + -> observed dynamic_front_rh_mm - (no known causal link)",
      "corroborated_by": 0
    },
    {
      "cause_param": "rear_spring_nmm",
      "cause_delta": 40.0,
      "effect_metric": "dynamic_rear_rh_mm",
      "effect_delta": 7.7659,
      "direction_match": false,
      "confidence": 0.1,
      "mechanism": "rear_spring_nmm + -> observed dynamic_rear_rh_mm + (no known causal link)",
      "corroborated_by": 0
    },
    {
      "cause_param": "rear_pushrod",
      "cause_delta": 1.0,
      "effect_metric": "front_rh_std_mm",
      "effect_delta": -0.6824,
      "direction_match": false,
      "confidence": 0.1,
      "mechanism": "rear_pushrod + -> observed front_rh_std_mm - (no known causal link)",
      "corroborated_by": 0
    },
    {
      "cause_param": "rear_pushrod",
      "cause_delta": 1.0,
      "effect_metric": "rear_rh_std_mm",
      "effect_delta": -1.4023,
      "direction_match": false,
      "confidence": 0.1,
      "mechanism": "rear_pushrod + -> observed rear_rh_std_mm - (no known causal link)",
      "corroborated_by": 0
    },
    {
      "cause_param": "rear_pushrod",
      "cause_delta": 1.0,
      "effect_metric": "rear_bottoming_events",
      "effect_delta": 2.0,
      "direction_match": false,
      "confidence": 0.1,
      "mechanism": "rear_pushrod + -> observed rear_bottoming_events + (no known causal link)",
      "corroborated_by": 0
    },
    {
      "cause_param": "rear_pushrod",
      "cause_delta": 1.0,
      "effect_metric": "front_shock_vel_p95_mps",
      "effect_delta": -0.0072,
      "direction_match": false,
      "confidence": 0.1,
      "mechanism": "rear_pushrod + -> observed front_shock_vel_p95_mps - (no known causal link)",
      "corroborated_by": 0
    },
    {
      "cause_param": "rear_pushrod",
      "cause_delta": 1.0,
      "effect_metric": "rear_shock_vel_p95_mps",
      "effect_delta": -0.0198,
      "direction_match": false,
      "confidence": 0.1,
      "mechanism": "rear_pushrod + -> observed rear_shock_vel_p95_mps - (no known causal link)",
      "corroborated_by": 0
    },
    {
      "cause_param": "rear_pushrod",
      "cause_delta": 1.0,
      "effect_metric": "understeer_high_speed_deg",
      "effect_delta": -0.0576,
      "direction_match": false,
      "confidence": 0.1,
      "mechanism": "rear_pushrod + -> observed understeer_high_speed_deg - (no known causal link)",
      "corroborated_by": 0
    },
    {
      "cause_param": "rear_pushrod",
      "cause_delta": 1.0,
      "effect_metric": "understeer_low_speed_deg",
      "effect_delta": 0.1485,
      "direction_match": false,
      "confidence": 0.1,
      "mechanism": "rear_pushrod + -> observed understeer_low_speed_deg + (no known causal link)",
      "corroborated_by": 0
    },
    {
      "cause_param": "rear_pushrod",
      "cause_delta": 1.0,
      "effect_metric": "dynamic_front_rh_mm",
      "effect_delta": -0.5496,
      "direction_match": false,
      "confidence": 0.1,
      "mechanism": "rear_pushrod + -> observed dynamic_front_rh_mm - (no known causal link)",
      "corroborated_by": 0
    },
    {
      "cause_param": "rear_pushrod",
      "cause_delta": 1.0,
      "effect_metric": "dynamic_rear_rh_mm",
      "effect_delta": 7.7659,
      "direction_match": false,
      "confidence": 0.1,
      "mechanism": "rear_pushrod + -> observed dynamic_rear_rh_mm + (no known causal link)",
      "corroborated_by": 0
    },
    {
      "cause_param": "rear_third_nmm",
      "cause_delta": 120.0,
      "effect_metric": "front_rh_std_mm",
      "effect_delta": -0.6824,
      "direction_match": false,
      "confidence": 0.1,
      "mechanism": "rear_third_nmm + -> observed front_rh_std_mm - (no known causal link)",
      "corroborated_by": 0
    },
    {
      "cause_param": "rear_third_nmm",
      "cause_delta": 120.0,
      "effect_metric": "rear_rh_std_mm",
      "effect_delta": -1.4023,
      "direction_match": true,
      "confidence": 0.8,
      "mechanism": "rear_third_nmm + -> expected rear_rh_std_mm -, observed -",
      "corroborated_by": 0
    },
    {
      "cause_param": "rear_third_nmm",
      "cause_delta": 120.0,
      "effect_metric": "rear_bottoming_events",
      "effect_delta": 2.0,
      "direction_match": false,
      "confidence": 0.3,
      "mechanism": "rear_third_nmm + -> expected rear_bottoming_events -, observed +",
      "corroborated_by": 0
    },
    {
      "cause_param": "rear_third_nmm",
      "cause_delta": 120.0,
      "effect_metric": "front_shock_vel_p95_mps",
      "effect_delta": -0.0072,
      "direction_match": false,
      "confidence": 0.1,
      "mechanism": "rear_third_nmm + -> observed front_shock_vel_p95_mps - (no known causal link)",
      "corroborated_by": 0
    },
    {
      "cause_param": "rear_third_nmm",
      "cause_delta": 120.0,
      "effect_metric": "rear_shock_vel_p95_mps",
      "effect_delta": -0.0198,
      "direction_match": false,
      "confidence": 0.1,
      "mechanism": "rear_third_nmm + -> observed rear_shock_vel_p95_mps - (no known causal link)",
      "corroborated_by": 0
    },
    {
      "cause_param": "rear_third_nmm",
      "cause_delta": 120.0,
      "effect_metric": "understeer_high_speed_deg",
      "effect_delta": -0.0576,
      "direction_match": false,
      "confidence": 0.1,
      "mechanism": "rear_third_nmm + -> observed understeer_high_speed_deg - (no known causal link)",
      "corroborated_by": 0
    },
    {
      "cause_param": "rear_third_nmm",
      "cause_delta": 120.0,
      "effect_metric": "understeer_low_speed_deg",
      "effect_delta": 0.1485,
      "direction_match": false,
      "confidence": 0.1,
      "mechanism": "rear_third_nmm + -> observed understeer_low_speed_deg + (no known causal link)",
      "corroborated_by": 0
    },
    {
      "cause_param": "rear_third_nmm",
      "cause_delta": 120.0,
      "effect_metric": "dynamic_front_rh_mm",
      "effect_delta": -0.5496,
      "direction_match": false,
      "confidence": 0.1,
      "mechanism": "rear_third_nmm + -> observed dynamic_front_rh_mm - (no known causal link)",
      "corroborated_by": 0
    },
    {
      "cause_param": "rear_third_nmm",
      "cause_delta": 120.0,
      "effect_metric": "dynamic_rear_rh_mm",
      "effect_delta": 7.7659,
      "direction_match": false,
      "confidence": 0.1,
      "mechanism": "rear_third_nmm + -> observed dynamic_rear_rh_mm + (no known causal link)",
      "corroborated_by": 0
    },
    {
      "cause_param": "front_pushrod",
      "cause_delta": -1.0,
      "effect_metric": "front_rh_std_mm",
      "effect_delta": -0.6824,
      "direction_match": false,
      "confidence": 0.1,
      "mechanism": "front_pushrod - -> observed front_rh_std_mm - (no known causal link)",
      "corroborated_by": 0
    },
    {
      "cause_param": "front_pushrod",
      "cause_delta": -1.0,
      "effect_metric": "rear_rh_std_mm",
      "effect_delta": -1.4023,
      "direction_match": false,
      "confidence": 0.1,
      "mechanism": "front_pushrod - -> observed rear_rh_std_mm - (no known causal link)",
      "corroborated_by": 0
    },
    {
      "cause_param": "front_pushrod",
      "cause_delta": -1.0,
      "effect_metric": "rear_bottoming_events",
      "effect_delta": 2.0,
      "direction_match": false,
      "confidence": 0.1,
      "mechanism": "front_pushrod - -> observed rear_bottoming_events + (no known causal link)",
      "corroborated_by": 0
    },
    {
      "cause_param": "front_pushrod",
      "cause_delta": -1.0,
      "effect_metric": "front_shock_vel_p95_mps",
      "effect_delta": -0.0072,
      "direction_match": false,
      "confidence": 0.1,
      "mechanism": "front_pushrod - -> observed front_shock_vel_p95_mps - (no known causal link)",
      "corroborated_by": 0
    },
    {
      "cause_param": "front_pushrod",
      "cause_delta": -1.0,
      "effect_metric": "rear_shock_vel_p95_mps",
      "effect_delta": -0.0198,
      "direction_match": false,
      "confidence": 0.1,
      "mechanism": "front_pushrod - -> observed rear_shock_vel_p95_mps - (no known causal link)",
      "corroborated_by": 0
    },
    {
      "cause_param": "front_pushrod",
      "cause_delta": -1.0,
      "effect_metric": "understeer_high_speed_deg",
      "effect_delta": -0.0576,
      "direction_match": false,
      "confidence": 0.1,
      "mechanism": "front_pushrod - -> observed understeer_high_speed_deg - (no known causal link)",
      "corroborated_by": 0
    },
    {
      "cause_param": "front_pushrod",
      "cause_delta": -1.0,
      "effect_metric": "understeer_low_speed_deg",
      "effect_delta": 0.1485,
      "direction_match": false,
      "confidence": 0.1,
      "mechanism": "front_pushrod - -> observed understeer_low_speed_deg + (no known causal link)",
      "corroborated_by": 0
    },
    {
      "cause_param": "front_pushrod",
      "cause_delta": -1.0,
      "effect_metric": "dynamic_front_rh_mm",
      "effect_delta": -0.5496,
      "direction_match": false,
      "confidence": 0.1,
      "mechanism": "front_pushrod - -> observed dynamic_front_rh_mm - (no known causal link)",
      "corroborated_by": 0
    },
    {
      "cause_param": "front_pushrod",
      "cause_delta": -1.0,
      "effect_metric": "dynamic_rear_rh_mm",
      "effect_delta": 7.7659,
      "direction_match": false,
      "confidence": 0.1,
      "mechanism": "front_pushrod - -> observed dynamic_rear_rh_mm + (no known causal link)",
      "corroborated_by": 0
    },
    {
      "cause_param": "rear_rh_static",
      "cause_delta": 4.200000000000003,
      "effect_metric": "front_rh_std_mm",
      "effect_delta": -0.6824,
      "direction_match": false,
      "confidence": 0.1,
      "mechanism": "rear_rh_static + -> observed front_rh_std_mm - (no known causal link)",
      "corroborated_by": 0
    },
    {
      "cause_param": "rear_rh_static",
      "cause_delta": 4.200000000000003,
      "effect_metric": "rear_rh_std_mm",
      "effect_delta": -1.4023,
      "direction_match": false,
      "confidence": 0.1,
      "mechanism": "rear_rh_static + -> observed rear_rh_std_mm - (no known causal link)",
      "corroborated_by": 0
    },
    {
      "cause_param": "rear_rh_static",
      "cause_delta": 4.200000000000003,
      "effect_metric": "rear_bottoming_events",
      "effect_delta": 2.0,
      "direction_match": false,
      "confidence": 0.1,
      "mechanism": "rear_rh_static + -> observed rear_bottoming_events + (no known causal link)",
      "corroborated_by": 0
    },
    {
      "cause_param": "rear_rh_static",
      "cause_delta": 4.200000000000003,
      "effect_metric": "front_shock_vel_p95_mps",
      "effect_delta": -0.0072,
      "direction_match": false,
      "confidence": 0.1,
      "mechanism": "rear_rh_static + -> observed front_shock_vel_p95_mps - (no known causal link)",
      "corroborated_by": 0
    },
    {
      "cause_param": "rear_rh_static",
      "cause_delta": 4.200000000000003,
      "effect_metric": "rear_shock_vel_p95_mps",
      "effect_delta": -0.0198,
      "direction_match": false,
      "confidence": 0.1,
      "mechanism": "rear_rh_static + -> observed rear_shock_vel_p95_mps - (no known causal link)",
      "corroborated_by": 0
    },
    {
      "cause_param": "rear_rh_static",
      "cause_delta": 4.200000000000003,
      "effect_metric": "understeer_high_speed_deg",
      "effect_delta": -0.0576,
      "direction_match": false,
      "confidence": 0.1,
      "mechanism": "rear_rh_static + -> observed understeer_high_speed_deg - (no known causal link)",
      "corroborated_by": 0
    },
    {
      "cause_param": "rear_rh_static",
      "cause_delta": 4.200000000000003,
      "effect_metric": "understeer_low_speed_deg",
      "effect_delta": 0.1485,
      "direction_match": false,
      "confidence": 0.1,
      "mechanism": "rear_rh_static + -> observed understeer_low_speed_deg + (no known causal link)",
      "corroborated_by": 0
    },
    {
      "cause_param": "rear_rh_static",
      "cause_delta": 4.200000000000003,
      "effect_metric": "dynamic_front_rh_mm",
      "effect_delta": -0.5496,
      "direction_match": false,
      "confidence": 0.1,
      "mechanism": "rear_rh_static + -> observed dynamic_front_rh_mm - (no known causal link)",
      "corroborated_by": 0
    },
    {
      "cause_param": "rear_rh_static",
      "cause_delta": 4.200000000000003,
      "effect_metric": "dynamic_rear_rh_mm",
      "effect_delta": 7.7659,
      "direction_match": false,
      "confidence": 0.1,
      "mechanism": "rear_rh_static + -> observed dynamic_rear_rh_mm + (no known causal link)",
      "corroborated_by": 0
    },
    {
      "cause_param": "rear_toe_mm",
      "cause_delta": -0.6,
      "effect_metric": "front_rh_std_mm",
      "effect_delta": -0.6824,
      "direction_match": false,
      "confidence": 0.1,
      "mechanism": "rear_toe_mm - -> observed front_rh_std_mm - (no known causal link)",
      "corroborated_by": 0
    },
    {
      "cause_param": "rear_toe_mm",
      "cause_delta": -0.6,
      "effect_metric": "rear_rh_std_mm",
      "effect_delta": -1.4023,
      "direction_match": false,
      "confidence": 0.1,
      "mechanism": "rear_toe_mm - -> observed rear_rh_std_mm - (no known causal link)",
      "corroborated_by": 0
    },
    {
      "cause_param": "rear_toe_mm",
      "cause_delta": -0.6,
      "effect_metric": "rear_bottoming_events",
      "effect_delta": 2.0,
      "direction_match": false,
      "confidence": 0.1,
      "mechanism": "rear_toe_mm - -> observed rear_bottoming_events + (no known causal link)",
      "corroborated_by": 0
    },
    {
      "cause_param": "rear_toe_mm",
      "cause_delta": -0.6,
      "effect_metric": "front_shock_vel_p95_mps",
      "effect_delta": -0.0072,
      "direction_match": false,
      "confidence": 0.1,
      "mechanism": "rear_toe_mm - -> observed front_shock_vel_p95_mps - (no known causal link)",
      "corroborated_by": 0
    },
    {
      "cause_param": "rear_toe_mm",
      "cause_delta": -0.6,
      "effect_metric": "rear_shock_vel_p95_mps",
      "effect_delta": -0.0198,
      "direction_match": false,
      "confidence": 0.1,
      "mechanism": "rear_toe_mm - -> observed rear_shock_vel_p95_mps - (no known causal link)",
      "corroborated_by": 0
    },
    {
      "cause_param": "rear_toe_mm",
      "cause_delta": -0.6,
      "effect_metric": "understeer_high_speed_deg",
      "effect_delta": -0.0576,
      "direction_match": false,
      "confidence": 0.1,
      "mechanism": "rear_toe_mm - -> observed understeer_high_speed_deg - (no known causal link)",
      "corroborated_by": 0
    },
    {
      "cause_param": "rear_toe_mm",
      "cause_delta": -0.6,
      "effect_metric": "understeer_low_speed_deg",
      "effect_delta": 0.1485,
      "direction_match": false,
      "confidence": 0.1,
      "mechanism": "rear_toe_mm - -> observed understeer_low_speed_deg + (no known causal link)",
      "corroborated_by": 0
    },
    {
      "cause_param": "rear_toe_mm",
      "cause_delta": -0.6,
      "effect_metric": "dynamic_front_rh_mm",
      "effect_delta": -0.5496,
      "direction_match": false,
      "confidence": 0.1,
      "mechanism": "rear_toe_mm - -> observed dynamic_front_rh_mm - (no known causal link)",
      "corroborated_by": 0
    },
    {
      "cause_param": "rear_toe_mm",
      "cause_delta": -0.6,
      "effect_metric": "dynamic_rear_rh_mm",
      "effect_delta": 7.7659,
      "direction_match": false,
      "confidence": 0.1,
      "mechanism": "rear_toe_mm - -> observed dynamic_rear_rh_mm + (no known causal link)",
      "corroborated_by": 0
    },
    {
      "cause_param": "damper_lr_ls_comp",
      "cause_delta": 1,
      "effect_metric": "front_rh_std_mm",
      "effect_delta": -0.6824,
      "direction_match": false,
      "confidence": 0.1,
      "mechanism": "damper_lr_ls_comp + -> observed front_rh_std_mm - (no known causal link)",
      "corroborated_by": 0
    },
    {
      "cause_param": "damper_lr_ls_comp",
      "cause_delta": 1,
      "effect_metric": "rear_rh_std_mm",
      "effect_delta": -1.4023,
      "direction_match": false,
      "confidence": 0.1,
      "mechanism": "damper_lr_ls_comp + -> observed rear_rh_std_mm - (no known causal link)",
      "corroborated_by": 0
    },
    {
      "cause_param": "damper_lr_ls_comp",
      "cause_delta": 1,
      "effect_metric": "rear_bottoming_events",
      "effect_delta": 2.0,
      "direction_match": false,
      "confidence": 0.1,
      "mechanism": "damper_lr_ls_comp + -> observed rear_bottoming_events + (no known causal link)",
      "corroborated_by": 0
    },
    {
      "cause_param": "damper_lr_ls_comp",
      "cause_delta": 1,
      "effect_metric": "front_shock_vel_p95_mps",
      "effect_delta": -0.0072,
      "direction_match": false,
      "confidence": 0.1,
      "mechanism": "damper_lr_ls_comp + -> observed front_shock_vel_p95_mps - (no known causal link)",
      "corroborated_by": 0
    },
    {
      "cause_param": "damper_lr_ls_comp",
      "cause_delta": 1,
      "effect_metric": "rear_shock_vel_p95_mps",
      "effect_delta": -0.0198,
      "direction_match": false,
      "confidence": 0.1,
      "mechanism": "damper_lr_ls_comp + -> observed rear_shock_vel_p95_mps - (no known causal link)",
      "corroborated_by": 0
    },
    {
      "cause_param": "damper_lr_ls_comp",
      "cause_delta": 1,
      "effect_metric": "understeer_high_speed_deg",
      "effect_delta": -0.0576,
      "direction_match": false,
      "confidence": 0.1,
      "mechanism": "damper_lr_ls_comp + -> observed understeer_high_speed_deg - (no known causal link)",
      "corroborated_by": 0
    },
    {
      "cause_param": "damper_lr_ls_comp",
      "cause_delta": 1,
      "effect_metric": "understeer_low_speed_deg",
      "effect_delta": 0.1485,
      "direction_match": false,
      "confidence": 0.1,
      "mechanism": "damper_lr_ls_comp + -> observed understeer_low_speed_deg + (no known causal link)",
      "corroborated_by": 0
    },
    {
      "cause_param": "damper_lr_ls_comp",
      "cause_delta": 1,
      "effect_metric": "dynamic_front_rh_mm",
      "effect_delta": -0.5496,
      "direction_match": false,
      "confidence": 0.1,
      "mechanism": "damper_lr_ls_comp + -> observed dynamic_front_rh_mm - (no known causal link)",
      "corroborated_by": 0
    },
    {
      "cause_param": "damper_lr_ls_comp",
      "cause_delta": 1,
      "effect_metric": "dynamic_rear_rh_mm",
      "effect_delta": 7.7659,
      "direction_match": false,
      "confidence": 0.1,
      "mechanism": "damper_lr_ls_comp + -> observed dynamic_rear_rh_mm + (no known causal link)",
      "corroborated_by": 0
    },
    {
      "cause_param": "damper_lr_ls_rbd",
      "cause_delta": 1,
      "effect_metric": "front_rh_std_mm",
      "effect_delta": -0.6824,
      "direction_match": false,
      "confidence": 0.1,
      "mechanism": "damper_lr_ls_rbd + -> observed front_rh_std_mm - (no known causal link)",
      "corroborated_by": 0
    },
    {
      "cause_param": "damper_lr_ls_rbd",
      "cause_delta": 1,
      "effect_metric": "rear_rh_std_mm",
      "effect_delta": -1.4023,
      "direction_match": false,
      "confidence": 0.1,
      "mechanism": "damper_lr_ls_rbd + -> observed rear_rh_std_mm - (no known causal link)",
      "corroborated_by": 0
    },
    {
      "cause_param": "damper_lr_ls_rbd",
      "cause_delta": 1,
      "effect_metric": "rear_bottoming_events",
      "effect_delta": 2.0,
      "direction_match": false,
      "confidence": 0.1,
      "mechanism": "damper_lr_ls_rbd + -> observed rear_bottoming_events + (no known causal link)",
      "corroborated_by": 0
    },
    {
      "cause_param": "damper_lr_ls_rbd",
      "cause_delta": 1,
      "effect_metric": "front_shock_vel_p95_mps",
      "effect_delta": -0.0072,
      "direction_match": false,
      "confidence": 0.1,
      "mechanism": "damper_lr_ls_rbd + -> observed front_shock_vel_p95_mps - (no known causal link)",
      "corroborated_by": 0
    },
    {
      "cause_param": "damper_lr_ls_rbd",
      "cause_delta": 1,
      "effect_metric": "rear_shock_vel_p95_mps",
      "effect_delta": -0.0198,
      "direction_match": false,
      "confidence": 0.1,
      "mechanism": "damper_lr_ls_rbd + -> observed rear_shock_vel_p95_mps - (no known causal link)",
      "corroborated_by": 0
    },
    {
      "cause_param": "damper_lr_ls_rbd",
      "cause_delta": 1,
      "effect_metric": "understeer_high_speed_deg",
      "effect_delta": -0.0576,
      "direction_match": false,
      "confidence": 0.1,
      "mechanism": "damper_lr_ls_rbd + -> observed understeer_high_speed_deg - (no known causal link)",
      "corroborated_by": 0
    },
    {
      "cause_param": "damper_lr_ls_rbd",
      "cause_delta": 1,
      "effect_metric": "understeer_low_speed_deg",
      "effect_delta": 0.1485,
      "direction_match": false,
      "confidence": 0.1,
      "mechanism": "damper_lr_ls_rbd + -> observed understeer_low_speed_deg + (no known causal link)",
      "corroborated_by": 0
    },
    {
      "cause_param": "damper_lr_ls_rbd",
      "cause_delta": 1,
      "effect_metric": "dynamic_front_rh_mm",
      "effect_delta": -0.5496,
      "direction_match": false,
      "confidence": 0.1,
      "mechanism": "damper_lr_ls_rbd + -> observed dynamic_front_rh_mm - (no known causal link)",
      "corroborated_by": 0
    },
    {
      "cause_param": "damper_lr_ls_rbd",
      "cause_delta": 1,
      "effect_metric": "dynamic_rear_rh_mm",
      "effect_delta": 7.7659,
      "direction_match": false,
      "confidence": 0.1,
      "mechanism": "damper_lr_ls_rbd + -> observed dynamic_rear_rh_mm + (no known causal link)",
      "corroborated_by": 0
    },
    {
      "cause_param": "damper_rr_ls_comp",
      "cause_delta": 1,
      "effect_metric": "front_rh_std_mm",
      "effect_delta": -0.6824,
      "direction_match": false,
      "confidence": 0.1,
      "mechanism": "damper_rr_ls_comp + -> observed front_rh_std_mm - (no known causal link)",
      "corroborated_by": 0
    },
    {
      "cause_param": "damper_rr_ls_comp",
      "cause_delta": 1,
      "effect_metric": "rear_rh_std_mm",
      "effect_delta": -1.4023,
      "direction_match": false,
      "confidence": 0.1,
      "mechanism": "damper_rr_ls_comp + -> observed rear_rh_std_mm - (no known causal link)",
      "corroborated_by": 0
    },
    {
      "cause_param": "damper_rr_ls_comp",
      "cause_delta": 1,
      "effect_metric": "rear_bottoming_events",
      "effect_delta": 2.0,
      "direction_match": false,
      "confidence": 0.1,
      "mechanism": "damper_rr_ls_comp + -> observed rear_bottoming_events + (no known causal link)",
      "corroborated_by": 0
    },
    {
      "cause_param": "damper_rr_ls_comp",
      "cause_delta": 1,
      "effect_metric": "front_shock_vel_p95_mps",
      "effect_delta": -0.0072,
      "direction_match": false,
      "confidence": 0.1,
      "mechanism": "damper_rr_ls_comp + -> observed front_shock_vel_p95_mps - (no known causal link)",
      "corroborated_by": 0
    },
    {
      "cause_param": "damper_rr_ls_comp",
      "cause_delta": 1,
      "effect_metric": "rear_shock_vel_p95_mps",
      "effect_delta": -0.0198,
      "direction_match": false,
      "confidence": 0.1,
      "mechanism": "damper_rr_ls_comp + -> observed rear_shock_vel_p95_mps - (no known causal link)",
      "corroborated_by": 0
    },
    {
      "cause_param": "damper_rr_ls_comp",
      "cause_delta": 1,
      "effect_metric": "understeer_high_speed_deg",
      "effect_delta": -0.0576,
      "direction_match": false,
      "confidence": 0.1,
      "mechanism": "damper_rr_ls_comp + -> observed understeer_high_speed_deg - (no known causal link)",
      "corroborated_by": 0
    },
    {
      "cause_param": "damper_rr_ls_comp",
      "cause_delta": 1,
      "effect_metric": "understeer_low_speed_deg",
      "effect_delta": 0.1485,
      "direction_match": false,
      "confidence": 0.1,
      "mechanism": "damper_rr_ls_comp + -> observed understeer_low_speed_deg + (no known causal link)",
      "corroborated_by": 0
    },
    {
      "cause_param": "damper_rr_ls_comp",
      "cause_delta": 1,
      "effect_metric": "dynamic_front_rh_mm",
      "effect_delta": -0.5496,
      "direction_match": false,
      "confidence": 0.1,
      "mechanism": "damper_rr_ls_comp + -> observed dynamic_front_rh_mm - (no known causal link)",
      "corroborated_by": 0
    },
    {
      "cause_param": "damper_rr_ls_comp",
      "cause_delta": 1,
      "effect_metric": "dynamic_rear_rh_mm",
      "effect_delta": 7.7659,
      "direction_match": false,
      "confidence": 0.1,
      "mechanism": "damper_rr_ls_comp + -> observed dynamic_rear_rh_mm + (no known causal link)",
      "corroborated_by": 0
    },
    {
      "cause_param": "damper_rr_ls_rbd",
      "cause_delta": 1,
      "effect_metric": "front_rh_std_mm",
      "effect_delta": -0.6824,
      "direction_match": false,
      "confidence": 0.1,
      "mechanism": "damper_rr_ls_rbd + -> observed front_rh_std_mm - (no known causal link)",
      "corroborated_by": 0
    },
    {
      "cause_param": "damper_rr_ls_rbd",
      "cause_delta": 1,
      "effect_metric": "rear_rh_std_mm",
      "effect_delta": -1.4023,
      "direction_match": false,
      "confidence": 0.1,
      "mechanism": "damper_rr_ls_rbd + -> observed rear_rh_std_mm - (no known causal link)",
      "corroborated_by": 0
    },
    {
      "cause_param": "damper_rr_ls_rbd",
      "cause_delta": 1,
      "effect_metric": "rear_bottoming_events",
      "effect_delta": 2.0,
      "direction_match": false,
      "confidence": 0.1,
      "mechanism": "damper_rr_ls_rbd + -> observed rear_bottoming_events + (no known causal link)",
      "corroborated_by": 0
    },
    {
      "cause_param": "damper_rr_ls_rbd",
      "cause_delta": 1,
      "effect_metric": "front_shock_vel_p95_mps",
      "effect_delta": -0.0072,
      "direction_match": false,
      "confidence": 0.1,
      "mechanism": "damper_rr_ls_rbd + -> observed front_shock_vel_p95_mps - (no known causal link)",
      "corroborated_by": 0
    },
    {
      "cause_param": "damper_rr_ls_rbd",
      "cause_delta": 1,
      "effect_metric": "rear_shock_vel_p95_mps",
      "effect_delta": -0.0198,
      "direction_match": false,
      "confidence": 0.1,
      "mechanism": "damper_rr_ls_rbd + -> observed rear_shock_vel_p95_mps - (no known causal link)",
      "corroborated_by": 0
    },
    {
      "cause_param": "damper_rr_ls_rbd",
      "cause_delta": 1,
      "effect_metric": "understeer_high_speed_deg",
      "effect_delta": -0.0576,
      "direction_match": false,
      "confidence": 0.1,
      "mechanism": "damper_rr_ls_rbd + -> observed understeer_high_speed_deg - (no known causal link)",
      "corroborated_by": 0
    },
    {
      "cause_param": "damper_rr_ls_rbd",
      "cause_delta": 1,
      "effect_metric": "understeer_low_speed_deg",
      "effect_delta": 0.1485,
      "direction_match": false,
      "confidence": 0.1,
      "mechanism": "damper_rr_ls_rbd + -> observed understeer_low_speed_deg + (no known causal link)",
      "corroborated_by": 0
    },
    {
      "cause_param": "damper_rr_ls_rbd",
      "cause_delta": 1,
      "effect_metric": "dynamic_front_rh_mm",
      "effect_delta": -0.5496,
      "direction_match": false,
      "confidence": 0.1,
      "mechanism": "damper_rr_ls_rbd + -> observed dynamic_front_rh_mm - (no known causal link)",
      "corroborated_by": 0
    },
    {
      "cause_param": "damper_rr_ls_rbd",
      "cause_delta": 1,
      "effect_metric": "dynamic_rear_rh_mm",
      "effect_delta": 7.7659,
      "direction_match": false,
      "confidence": 0.1,
      "mechanism": "damper_rr_ls_rbd + -> observed dynamic_rear_rh_mm + (no known causal link)",
      "corroborated_by": 0
    }
  ],
  "num_setup_changes": 11,
  "controlled_experiment": false,
  "changed_steps": [
    "step1_rake",
    "step2_heave",
    "step3_springs",
    "step5_geometry",
    "step6_dampers"
  ],
  "lap_time_delta_s": -0.74,
  "driver_style_changed": false,
  "key_finding": "Changed rear_spring_nmm: 40.0, rear_third_nmm: 120.0, rear_toe_mm: -0.6 (0.740s faster); effects: understeer_high_speed_deg -0.06, understeer_low_speed_deg +0.15, dynamic_rear_rh_mm +7.77 [low confidence]",
  "confidence_level": "low"
}